datasette_pytables/__init__.py
datasette_pytables/monkey.py
datasette_pytables/utils.py
datasette_pytables-2.0.1.dist-info/LICENSE
datasette_pytables-2.0.1.dist-info/METADATA
datasette_pytables-2.0.1.dist-info/WHEEL
datasette_pytables-2.0.1.dist-info/entry_points.txt
datasette_pytables-2.0.1.dist-info/top_level.txt
datasette_pytables-2.0.1.dist-info/RECORD
