Metadata-Version: 2.1
Name: datasette-pytables
Version: 2.0.1
Summary: Datasette connector for loading pytables files (.h5)
Home-page: https://github.com/jsancho-gpl/datasette-pytables
Author: Javier Sancho
Author-email: jsf@jsancho.org
License: Apache License, Version 2.0
Platform: UNKNOWN
Requires-Dist: datasette-connectors (>=2.0.0)
Requires-Dist: mo-future (==3.89.20246)
Requires-Dist: moz-sql-parser (==3.32.20026)
Requires-Dist: tables
